Play_mp3/__init__.py
play_mp3-0.0.1.dist-info/LICENSE.txt
play_mp3-0.0.1.dist-info/METADATA
play_mp3-0.0.1.dist-info/WHEEL
play_mp3-0.0.1.dist-info/top_level.txt
play_mp3-0.0.1.dist-info/RECORD
